tracksuite/__init__.py
tracksuite/_version.py
tracksuite/definition.py
tracksuite/deploy.py
tracksuite/ecflow_client.py
tracksuite/init.py
tracksuite/print.py
tracksuite/replace.py
tracksuite/repos.py
tracksuite/revert.py
tracksuite/utils.py
tracksuite-0.5.0.dist-info/licenses/LICENSE
tracksuite-0.5.0.dist-info/METADATA
tracksuite-0.5.0.dist-info/WHEEL
tracksuite-0.5.0.dist-info/entry_points.txt
tracksuite-0.5.0.dist-info/top_level.txt
tracksuite-0.5.0.dist-info/RECORD
