Metadata-Version: 2.4
Name: tracksuite
Version: 0.5.0
Summary: ecflow suite tracking and deploying toolkit
Author-email: "European Centre for Medium-Range Weather Forecasts (ECMWF)" <software.support@ecmwf.int>, Corentin Carton de Wiart <corentin.carton@ecmwf.int>
License: Apache License Version 2.0
Project-URL: Source code, https://github.com/ecmwf/tracksuite
Classifier: Development Status :: 4 - Beta
Classifier: Intended Audience :: Developers
Classifier: License :: OSI Approved :: Apache Software License
Classifier: Operating System :: Unix
Classifier: Programming Language :: Python :: 3
Classifier: Topic :: Scientific/Engineering
Requires-Python: >=3.8
License-File: LICENSE
Requires-Dist: gitpython>=3.1.25
Provides-Extra: test
Requires-Dist: pytest; extra == "test"
Requires-Dist: mocker; extra == "test"
Requires-Dist: pytest-mock; extra == "test"
Dynamic: license-file
